{
  "hash": "37b202bd",
  "configHash": "69026f58",
  "lockfileHash": "bccbeadb",
  "browserHash": "9a17f842",
  "optimized": {
    "react": {
      "src": "../../node_modules/react/index.js",
      "file": "react.js",
      "fileHash": "c197b5a6",
      "needsInterop": true
    },
    "react-dom/client": {
      "src": "../../node_modules/react-dom/client.js",
      "file": "react-dom_client.js",
      "fileHash": "de31be27",
      "needsInterop": true
    },
    "firebase/firestore": {
      "src": "../../node_modules/firebase/firestore/dist/esm/index.esm.js",
      "file": "firebase_firestore.js",
      "fileHash": "4703d239",
      "needsInterop": false
    },
    "lucide-react": {
      "src": "../../node_modules/lucide-react/dist/esm/lucide-react.js",
      "file": "lucide-react.js",
      "fileHash": "12a4cf2e",
      "needsInterop": false
    },
    "firebase/app": {
      "src": "../../node_modules/firebase/app/dist/esm/index.esm.js",
      "file": "firebase_app.js",
      "fileHash": "52452817",
      "needsInterop": false
    },
    "firebase/auth": {
      "src": "../../node_modules/firebase/auth/dist/esm/index.esm.js",
      "file": "firebase_auth.js",
      "fileHash": "c32ece28",
      "needsInterop": false
    }
  },
  "chunks": {
    "chunk-32E4H3EV": {
      "file": "chunk-32E4H3EV.js"
    },
    "chunk-5CMO42JT": {
      "file": "chunk-5CMO42JT.js"
    },
    "chunk-G3PMV62Z": {
      "file": "chunk-G3PMV62Z.js"
    }
  }
}